{
  "parent": "synthetics:artificial_capillaries",
  "id": "synthetics:artificial_tissue",
  "requirements": {
    "experience_cost": 75,
    "required_items": [
      {
        "amount": 32,
        "item": {
          "item": "minecraft:rotten_flesh"
        }
      },
      {
        "amount": 12,
        "item": {
          "item": "minecraft:string"
        }
      },
      {
        "amount": 32,
        "item": {
          "item": "minecraft:clay"
        }
      }
    ]
  },
  "tab": "synthetics:body_parts",
  "unlocked": {
    "item": {
      "item": "synthetics:artificial_tissue"
    }
  },
  "x": 30,
  "y": 90
}