{
  "parent": "synthetics:artificial_tissue",
  "id": "synthetics:organic_hands",
  "requirements": {
    "experience_cost": 175,
    "required_items": [
      {
        "amount": 4,
        "item": {
          "item": "minecraft:bone"
        }
      },
      {
        "amount": 12,
        "item": {
          "item": "synthetics:artificial_capillary"
        }
      },
      {
        "amount": 8,
        "item": {
          "item": "synthetics:artificial_tissue"
        }
      },
      {
        "amount": 12,
        "item": {
          "item": "synthetics:artificial_neuron"
        }
      }
    ]
  },
  "unlocked": {
    "parts": "synthetics:organic_hands"
  },
  "x": 110,
  "y": 190
}